pokemanager/__init__.py
pokemanager/_version.py
pokemanager/cli.py
pokemanager/const.py
pokemanager/data.py
pokemanager/main.py
pokemanager/utils.py
pokemanager/cli_commands/cli_box.py
pokemanager/cli_commands/cli_config.py
pokemanager/cli_commands/cli_fetch.py
pokemanager/cli_commands/cli_pokemon.py
pokemanager/cli_commands/utils.py
pokemanager-0.1.3.dist-info/licenses/LICENSE
pokemanager-0.1.3.dist-info/METADATA
pokemanager-0.1.3.dist-info/WHEEL
pokemanager-0.1.3.dist-info/entry_points.txt
pokemanager-0.1.3.dist-info/top_level.txt
pokemanager-0.1.3.dist-info/RECORD
