Metadata-Version: 2.4
Name: pokemanager
Version: 0.1.3
Summary: A suite of tools for analysing Pokémon teams.
Author-email: Ethan Shanahan <ethan.shanahan@gmail.com>
License-Expression: GPL-3.0-or-later
Project-URL: Documentation, http://pokemanager.readthedocs.io/en/latest/
Project-URL: Source, https://github.com/ethan-shanahan/pokemanager
Keywords: pokemon,analysis
Classifier: Natural Language :: English
Classifier: Programming Language :: Python
Classifier: Operating System :: OS Independent
Classifier: Intended Audience :: End Users/Desktop
Classifier: Development Status :: 3 - Alpha
Requires-Python: >=3.11
License-File: LICENSE
Requires-Dist: gspread
Dynamic: license-file
